[
    {
        "timestamp": 1572430512,
        "computerName": "Oculus",
        "isFail": false,
        "isQuit": false,
        "player": "CHELS",
        "song": "TheGreatestShow",
        "difficulty": "Hard",
        "score": 116899,
        "fullCombo": false,
        "modifiers": {
            "energyType": 0,
            "noFail": true,
            "instaFail": false,
            "failOnSaberClash": false,
            "enabledObstacleType": 0,
            "fastNotes": false,
            "strictAngles": false,
            "disappearingArrows": false,
            "ghostNotes": false,
            "noBombs": false,
            "songSpeed": 0
        },
        "settings": {
            "staticLights": false,
            "leftHanded": false,
            "playerHeight": 1.1877484321594238,
            "disableSFX": false,
            "reduceDebris": false,
            "noTextsAndHuds": false,
            "advancedHud": true
        },
        "gameStats": {
            "badCutsCount": 7,
            "cutScoreWithoutMultiplier": 35870,
            "goodCutsCount": 422,
            "handDistanceTravelled": 404,
            "missedCutsCount": 11,
            "timePlayed": 168.125,
            "totalScore": 116899
        }
    },
    {
        "timestamp": 1572430336,
        "computerName": "Oculus",
        "isFail": false,
        "isQuit": false,
        "player": "CHELS",
        "song": "TheGreatestShow",
        "difficulty": "Hard",
        "score": 109757,
        "fullCombo": false,
        "modifiers": {
            "energyType": 0,
            "noFail": true,
            "instaFail": false,
            "failOnSaberClash": false,
            "enabledObstacleType": 0,
            "fastNotes": false,
            "strictAngles": false,
            "disappearingArrows": false,
            "ghostNotes": false,
            "noBombs": false,
            "songSpeed": 0
        },
        "settings": {
            "staticLights": false,
            "leftHanded": false,
            "playerHeight": 1.1877484321594238,
            "disableSFX": false,
            "reduceDebris": false,
            "noTextsAndHuds": false,
            "advancedHud": true
        },
        "gameStats": {
            "badCutsCount": 16,
            "cutScoreWithoutMultiplier": 36668,
            "goodCutsCount": 412,
            "handDistanceTravelled": 438,
            "missedCutsCount": 12,
            "timePlayed": 168.125,
            "totalScore": 109757
        }
    },
    {
        "timestamp": 1572430289,
        "computerName": "budid",
        "isFail": false,
        "isQuit": false,
        "player": "GHOSTYYYY",
        "song": "custom_level_7C7F38D467BB43FE11A142581E63E324622ECC71",
        "difficulty": "Hard",
        "score": 62122,
        "fullCombo": false,
        "modifiers": {
            "energyType": 0,
            "noFail": true,
            "instaFail": false,
            "failOnSaberClash": false,
            "enabledObstacleType": 0,
            "fastNotes": false,
            "strictAngles": false,
            "disappearingArrows": false,
            "ghostNotes": false,
            "noBombs": false,
            "songSpeed": 2
        },
        "settings": {
            "staticLights": false,
            "leftHanded": false,
            "playerHeight": 1.6266272068023682,
            "disableSFX": false,
            "reduceDebris": false,
            "noTextsAndHuds": false,
            "advancedHud": true
        },
        "gameStats": {
            "badCutsCount": 1,
            "cutScoreWithoutMultiplier": 43160,
            "goodCutsCount": 415,
            "handDistanceTravelled": 1208,
            "missedCutsCount": 5,
            "timePlayed": 190.3125,
            "totalScore": 62122
        }
    },
    {
        "timestamp": 1572430162,
        "computerName": "Oculus",
        "isFail": false,
        "isQuit": false,
        "player": "CHELS",
        "song": "TheGreatestShow",
        "difficulty": "Hard",
        "score": 120827,
        "fullCombo": false,
        "modifiers": {
            "energyType": 0,
            "noFail": true,
            "instaFail": false,
            "failOnSaberClash": false,
            "enabledObstacleType": 0,
            "fastNotes": false,
            "strictAngles": false,
            "disappearingArrows": false,
            "ghostNotes": false,
            "noBombs": false,
            "songSpeed": 0
        },
        "settings": {
            "staticLights": false,
            "leftHanded": false,
            "playerHeight": 1.1877484321594238,
            "disableSFX": false,
            "reduceDebris": false,
            "noTextsAndHuds": false,
            "advancedHud": true
        },
        "gameStats": {
            "badCutsCount": 7,
            "cutScoreWithoutMultiplier": 37291,
            "goodCutsCount": 419,
            "handDistanceTravelled": 442,
            "missedCutsCount": 14,
            "timePlayed": 168.125,
            "totalScore": 120827
        }
    },
    {
        "timestamp": 1572430160,
        "song": "#unknown",
        "isFail": false,
        "isQuit": false,
        "computerName": "Oculus",
        "player": "UNKNOWN",
        "score": 120827,
        "modifiers": {
            "energyType": 0,
            "noFail": true,
            "instaFail": false,
            "failOnSaberClash": false,
            "enabledObstacleType": 0,
            "fastNotes": false,
            "strictAngles": false,
            "disappearingArrows": false,
            "ghostNotes": false,
            "noBombs": false,
            "songSpeed": 0
        },
        "settings": {
            "staticLights": false,
            "leftHanded": false,
            "playerHeight": 1.1877484321594238,
            "disableSFX": false,
            "reduceDebris": false,
            "noTextsAndHuds": false,
            "advancedHud": true
        },
        "gameStats": {
            "badCutsCount": 7,
            "cutScoreWithoutMultiplier": 37291,
            "goodCutsCount": 419,
            "handDistanceTravelled": 442,
            "missedCutsCount": 14,
            "timePlayed": 168.125,
            "totalScore": 120827
        }
    },
    {
        "timestamp": 1572429921,
        "computerName": "budid",
        "isFail": false,
        "isQuit": false,
        "player": "V",
        "song": "custom_level_2AA1F5192828E075C30DD015B1E132BBA912EB86",
        "difficulty": "Expert",
        "score": 263016,
        "fullCombo": false,
        "modifiers": {
            "energyType": 0,
            "noFail": false,
            "instaFail": false,
            "failOnSaberClash": false,
            "enabledObstacleType": 0,
            "fastNotes": false,
            "strictAngles": false,
            "disappearingArrows": false,
            "ghostNotes": false,
            "noBombs": false,
            "songSpeed": 0
        },
        "settings": {
            "staticLights": false,
            "leftHanded": false,
            "playerHeight": 1.6266272068023682,
            "disableSFX": false,
            "reduceDebris": false,
            "noTextsAndHuds": false,
            "advancedHud": true
        },
        "gameStats": {
            "badCutsCount": 22,
            "cutScoreWithoutMultiplier": 39900,
            "goodCutsCount": 475,
            "handDistanceTravelled": 441,
            "missedCutsCount": 8,
            "timePlayed": 139.234375,
            "totalScore": 263016
        }
    },
    {
        "timestamp": 1572429916,
        "computerName": "Oculus",
        "isFail": false,
        "isQuit": false,
        "player": "CHELS",
        "song": "HighHopes",
        "difficulty": "Normal",
        "score": 97987,
        "fullCombo": false,
        "modifiers": {
            "energyType": 0,
            "noFail": true,
            "instaFail": false,
            "failOnSaberClash": false,
            "enabledObstacleType": 0,
            "fastNotes": false,
            "strictAngles": false,
            "disappearingArrows": false,
            "ghostNotes": false,
            "noBombs": false,
            "songSpeed": 0
        },
        "settings": {
            "staticLights": false,
            "leftHanded": false,
            "playerHeight": 1.1877484321594238,
            "disableSFX": false,
            "reduceDebris": false,
            "noTextsAndHuds": false,
            "advancedHud": true
        },
        "gameStats": {
            "badCutsCount": 5,
            "cutScoreWithoutMultiplier": 28308,
            "goodCutsCount": 337,
            "handDistanceTravelled": 398,
            "missedCutsCount": 6,
            "timePlayed": 191.5,
            "totalScore": 97987
        }
    },
    {
        "timestamp": 1572429735,
        "song": "#unknown",
        "isFail": false,
        "isQuit": true,
        "computerName": "budid",
        "player": "UNKNOWN",
        "score": 0,
        "modifiers": {
            "energyType": 0,
            "noFail": false,
            "instaFail": false,
            "failOnSaberClash": false,
            "enabledObstacleType": 0,
            "fastNotes": false,
            "strictAngles": false,
            "disappearingArrows": false,
            "ghostNotes": false,
            "noBombs": false,
            "songSpeed": 1
        },
        "settings": {
            "staticLights": false,
            "leftHanded": false,
            "playerHeight": 1.6266272068023682,
            "disableSFX": false,
            "reduceDebris": false,
            "noTextsAndHuds": false,
            "advancedHud": true
        },
        "gameStats": {
            "badCutsCount": 3,
            "cutScoreWithoutMultiplier": 25792,
            "goodCutsCount": 248,
            "handDistanceTravelled": 399,
            "missedCutsCount": 2,
            "timePlayed": 79.53125,
            "totalScore": 0
        }
    },
    {
        "timestamp": 1572429706,
        "computerName": "Oculus",
        "isFail": false,
        "isQuit": false,
        "player": "CHELS",
        "song": "TheGreatestShow",
        "difficulty": "Normal",
        "score": 89833,
        "fullCombo": false,
        "modifiers": {
            "energyType": 0,
            "noFail": true,
            "instaFail": false,
            "failOnSaberClash": false,
            "enabledObstacleType": 0,
            "fastNotes": false,
            "strictAngles": false,
            "disappearingArrows": false,
            "ghostNotes": false,
            "noBombs": false,
            "songSpeed": 0
        },
        "settings": {
            "staticLights": false,
            "leftHanded": false,
            "playerHeight": 1.1877484321594238,
            "disableSFX": false,
            "reduceDebris": false,
            "noTextsAndHuds": false,
            "advancedHud": true
        },
        "gameStats": {
            "badCutsCount": 3,
            "cutScoreWithoutMultiplier": 24728,
            "goodCutsCount": 281,
            "handDistanceTravelled": 403,
            "missedCutsCount": 1,
            "timePlayed": 168.125,
            "totalScore": 89833
        }
    },
    {
        "timestamp": 1572429703,
        "song": "#unknown",
        "isFail": false,
        "isQuit": false,
        "computerName": "Oculus",
        "player": "UNKNOWN",
        "score": 89833,
        "modifiers": {
            "energyType": 0,
            "noFail": true,
            "instaFail": false,
            "failOnSaberClash": false,
            "enabledObstacleType": 0,
            "fastNotes": false,
            "strictAngles": false,
            "disappearingArrows": false,
            "ghostNotes": false,
            "noBombs": false,
            "songSpeed": 0
        },
        "settings": {
            "staticLights": false,
            "leftHanded": false,
            "playerHeight": 1.1877484321594238,
            "disableSFX": false,
            "reduceDebris": false,
            "noTextsAndHuds": false,
            "advancedHud": true
        },
        "gameStats": {
            "badCutsCount": 3,
            "cutScoreWithoutMultiplier": 24728,
            "goodCutsCount": 281,
            "handDistanceTravelled": 403,
            "missedCutsCount": 1,
            "timePlayed": 168.125,
            "totalScore": 89833
        }
    },
    {
        "timestamp": 1572429611,
        "song": "#unknown",
        "isFail": false,
        "isQuit": true,
        "computerName": "budid",
        "player": "UNKNOWN",
        "score": 0,
        "modifiers": {
            "energyType": 0,
            "noFail": false,
            "instaFail": false,
            "failOnSaberClash": false,
            "enabledObstacleType": 0,
            "fastNotes": false,
            "strictAngles": false,
            "disappearingArrows": false,
            "ghostNotes": false,
            "noBombs": false,
            "songSpeed": 1
        },
        "settings": {
            "staticLights": false,
            "leftHanded": false,
            "playerHeight": 1.504594087600708,
            "disableSFX": false,
            "reduceDebris": false,
            "noTextsAndHuds": false,
            "advancedHud": true
        },
        "gameStats": {
            "badCutsCount": 0,
            "cutScoreWithoutMultiplier": 1484,
            "goodCutsCount": 14,
            "handDistanceTravelled": 43,
            "missedCutsCount": 0,
            "timePlayed": 12.921875,
            "totalScore": 0
        }
    },
    {
        "timestamp": 1572429504,
        "computerName": "Oculus",
        "isFail": false,
        "isQuit": false,
        "player": "CHELS",
        "song": "Thunder",
        "difficulty": "Normal",
        "score": 99775,
        "fullCombo": false,
        "modifiers": {
            "energyType": 0,
            "noFail": true,
            "instaFail": false,
            "failOnSaberClash": false,
            "enabledObstacleType": 0,
            "fastNotes": false,
            "strictAngles": false,
            "disappearingArrows": false,
            "ghostNotes": false,
            "noBombs": false,
            "songSpeed": 0
        },
        "settings": {
            "staticLights": false,
            "leftHanded": false,
            "playerHeight": 1.1877484321594238,
            "disableSFX": false,
            "reduceDebris": false,
            "noTextsAndHuds": false,
            "advancedHud": true
        },
        "gameStats": {
            "badCutsCount": 6,
            "cutScoreWithoutMultiplier": 27950,
            "goodCutsCount": 325,
            "handDistanceTravelled": 413,
            "missedCutsCount": 3,
            "timePlayed": 177.375,
            "totalScore": 99775
        }
    },
    {
        "timestamp": 1572429496,
        "song": "#unknown",
        "isFail": false,
        "isQuit": false,
        "computerName": "Oculus",
        "player": "UNKNOWN",
        "score": 99775,
        "modifiers": {
            "energyType": 0,
            "noFail": true,
            "instaFail": false,
            "failOnSaberClash": false,
            "enabledObstacleType": 0,
            "fastNotes": false,
            "strictAngles": false,
            "disappearingArrows": false,
            "ghostNotes": false,
            "noBombs": false,
            "songSpeed": 0
        },
        "settings": {
            "staticLights": false,
            "leftHanded": false,
            "playerHeight": 1.1877484321594238,
            "disableSFX": false,
            "reduceDebris": false,
            "noTextsAndHuds": false,
            "advancedHud": true
        },
        "gameStats": {
            "badCutsCount": 6,
            "cutScoreWithoutMultiplier": 27950,
            "goodCutsCount": 325,
            "handDistanceTravelled": 413,
            "missedCutsCount": 3,
            "timePlayed": 177.375,
            "totalScore": 99775
        }
    },
    {
        "timestamp": 1572419189,
        "computerName": "budid",
        "isFail": false,
        "isQuit": false,
        "player": "NDR",
        "song": "BadLiar",
        "difficulty": "Hard",
        "score": 213683,
        "fullCombo": false,
        "modifiers": {
            "energyType": 0,
            "noFail": true,
            "instaFail": false,
            "failOnSaberClash": false,
            "enabledObstacleType": 0,
            "fastNotes": false,
            "strictAngles": false,
            "disappearingArrows": false,
            "ghostNotes": false,
            "noBombs": false,
            "songSpeed": 0
        },
        "settings": {
            "staticLights": false,
            "leftHanded": false,
            "playerHeight": 1.504594087600708,
            "disableSFX": false,
            "reduceDebris": false,
            "noTextsAndHuds": false,
            "advancedHud": true
        },
        "gameStats": {
            "badCutsCount": 10,
            "cutScoreWithoutMultiplier": 57380,
            "goodCutsCount": 604,
            "handDistanceTravelled": 804,
            "missedCutsCount": 5,
            "timePlayed": 252.40625,
            "totalScore": 213683
        }
    },
    {
        "timestamp": 1572418914,
        "computerName": "budid",
        "isFail": false,
        "isQuit": false,
        "player": "NDR",
        "song": "TheGreatestShow",
        "difficulty": "Hard",
        "score": 174809,
        "fullCombo": true,
        "modifiers": {
            "energyType": 0,
            "noFail": true,
            "instaFail": false,
            "failOnSaberClash": false,
            "enabledObstacleType": 0,
            "fastNotes": false,
            "strictAngles": false,
            "disappearingArrows": false,
            "ghostNotes": false,
            "noBombs": false,
            "songSpeed": 0
        },
        "settings": {
            "staticLights": false,
            "leftHanded": false,
            "playerHeight": 1.504594087600708,
            "disableSFX": false,
            "reduceDebris": false,
            "noTextsAndHuds": false,
            "advancedHud": true
        },
        "gameStats": {
            "badCutsCount": 0,
            "cutScoreWithoutMultiplier": 44000,
            "goodCutsCount": 440,
            "handDistanceTravelled": 640,
            "missedCutsCount": 0,
            "timePlayed": 168.109375,
            "totalScore": 174809
        }
    },
    {
        "timestamp": 1572418661,
        "computerName": "budid",
        "isFail": false,
        "isQuit": false,
        "player": "GHOSTYYYY",
        "song": "ThisTime",
        "difficulty": "Normal",
        "score": 184450,
        "fullCombo": false,
        "modifiers": {
            "energyType": 0,
            "noFail": false,
            "instaFail": false,
            "failOnSaberClash": false,
            "enabledObstacleType": 2,
            "fastNotes": false,
            "strictAngles": false,
            "disappearingArrows": false,
            "ghostNotes": false,
            "noBombs": true,
            "songSpeed": 0
        },
        "settings": {
            "staticLights": false,
            "leftHanded": false,
            "playerHeight": 1.504594087600708,
            "disableSFX": false,
            "reduceDebris": false,
            "noTextsAndHuds": false,
            "advancedHud": true
        },
        "gameStats": {
            "badCutsCount": 4,
            "cutScoreWithoutMultiplier": 29000,
            "goodCutsCount": 290,
            "handDistanceTravelled": 643,
            "missedCutsCount": 0,
            "timePlayed": 170.40625,
            "totalScore": 184450
        }
    },
    {
        "timestamp": 1572418468,
        "computerName": "budid",
        "isFail": false,
        "isQuit": false,
        "player": "GHOSTYYYY",
        "song": "ThisTime",
        "difficulty": "Normal",
        "score": 11251,
        "fullCombo": false,
        "modifiers": {
            "energyType": 0,
            "noFail": true,
            "instaFail": false,
            "failOnSaberClash": false,
            "enabledObstacleType": 2,
            "fastNotes": false,
            "strictAngles": false,
            "disappearingArrows": false,
            "ghostNotes": false,
            "noBombs": true,
            "songSpeed": 2
        },
        "settings": {
            "staticLights": false,
            "leftHanded": false,
            "playerHeight": 1.504594087600708,
            "disableSFX": false,
            "reduceDebris": false,
            "noTextsAndHuds": false,
            "advancedHud": true
        },
        "gameStats": {
            "badCutsCount": 1,
            "cutScoreWithoutMultiplier": 28714,
            "goodCutsCount": 293,
            "handDistanceTravelled": 632,
            "missedCutsCount": 0,
            "timePlayed": 144.84375,
            "totalScore": 11251
        }
    },
    {
        "timestamp": 1572414625,
        "computerName": "budid",
        "isFail": false,
        "isQuit": false,
        "player": "DRACO",
        "song": "Origins",
        "difficulty": "Expert",
        "score": 422780,
        "fullCombo": false,
        "modifiers": {
            "energyType": 0,
            "noFail": false,
            "instaFail": false,
            "failOnSaberClash": false,
            "enabledObstacleType": 0,
            "fastNotes": false,
            "strictAngles": false,
            "disappearingArrows": false,
            "ghostNotes": false,
            "noBombs": false,
            "songSpeed": 0
        },
        "settings": {
            "staticLights": false,
            "leftHanded": false,
            "playerHeight": 1.504594087600708,
            "disableSFX": false,
            "reduceDebris": false,
            "noTextsAndHuds": false,
            "advancedHud": true
        },
        "gameStats": {
            "badCutsCount": 1,
            "cutScoreWithoutMultiplier": 55744,
            "goodCutsCount": 536,
            "handDistanceTravelled": 759,
            "missedCutsCount": 5,
            "timePlayed": 147.921875,
            "totalScore": 422780
        }
    },
    {
        "timestamp": 1572414458,
        "computerName": "budid",
        "isFail": false,
        "isQuit": false,
        "player": "DRACO",
        "song": "PopStars",
        "difficulty": "Expert",
        "score": 656284,
        "fullCombo": true,
        "modifiers": {
            "energyType": 0,
            "noFail": false,
            "instaFail": false,
            "failOnSaberClash": false,
            "enabledObstacleType": 0,
            "fastNotes": false,
            "strictAngles": false,
            "disappearingArrows": true,
            "ghostNotes": false,
            "noBombs": false,
            "songSpeed": 1
        },
        "settings": {
            "staticLights": false,
            "leftHanded": false,
            "playerHeight": 1.504594087600708,
            "disableSFX": false,
            "reduceDebris": false,
            "noTextsAndHuds": false,
            "advancedHud": true
        },
        "gameStats": {
            "badCutsCount": 0,
            "cutScoreWithoutMultiplier": 71974,
            "goodCutsCount": 679,
            "handDistanceTravelled": 1037,
            "missedCutsCount": 0,
            "timePlayed": 227.109375,
            "totalScore": 656284
        }
    },
    {
        "timestamp": 1572414261,
        "computerName": "budid",
        "isFail": false,
        "isQuit": false,
        "player": "DRACO",
        "song": "Victorious",
        "difficulty": "Expert",
        "score": 485323,
        "fullCombo": false,
        "modifiers": {
            "energyType": 0,
            "noFail": false,
            "instaFail": false,
            "failOnSaberClash": false,
            "enabledObstacleType": 0,
            "fastNotes": false,
            "strictAngles": false,
            "disappearingArrows": true,
            "ghostNotes": false,
            "noBombs": true,
            "songSpeed": 0
        },
        "settings": {
            "staticLights": false,
            "leftHanded": false,
            "playerHeight": 1.504594087600708,
            "disableSFX": false,
            "reduceDebris": false,
            "noTextsAndHuds": false,
            "advancedHud": true
        },
        "gameStats": {
            "badCutsCount": 10,
            "cutScoreWithoutMultiplier": 68880,
            "goodCutsCount": 656,
            "handDistanceTravelled": 1056,
            "missedCutsCount": 8,
            "timePlayed": 175.984375,
            "totalScore": 485323
        }
    },
    {
        "timestamp": 1572414072,
        "computerName": "budid",
        "isFail": false,
        "isQuit": false,
        "player": "DRACO",
        "song": "Victorious",
        "difficulty": "Expert",
        "score": 534903,
        "fullCombo": false,
        "modifiers": {
            "energyType": 0,
            "noFail": false,
            "instaFail": false,
            "failOnSaberClash": false,
            "enabledObstacleType": 0,
            "fastNotes": false,
            "strictAngles": false,
            "disappearingArrows": false,
            "ghostNotes": false,
            "noBombs": false,
            "songSpeed": 0
        },
        "settings": {
            "staticLights": false,
            "leftHanded": false,
            "playerHeight": 1.504594087600708,
            "disableSFX": false,
            "reduceDebris": false,
            "noTextsAndHuds": false,
            "advancedHud": true
        },
        "gameStats": {
            "badCutsCount": 4,
            "cutScoreWithoutMultiplier": 70702,
            "goodCutsCount": 667,
            "handDistanceTravelled": 1035,
            "missedCutsCount": 3,
            "timePlayed": 175.984375,
            "totalScore": 534903
        }
    },
    {
        "timestamp": 1572413888,
        "song": "#unknown",
        "isFail": false,
        "isQuit": true,
        "computerName": "budid",
        "player": "UNKNOWN",
        "score": 0,
        "modifiers": {
            "energyType": 0,
            "noFail": false,
            "instaFail": false,
            "failOnSaberClash": false,
            "enabledObstacleType": 0,
            "fastNotes": false,
            "strictAngles": false,
            "disappearingArrows": false,
            "ghostNotes": false,
            "noBombs": false,
            "songSpeed": 0
        },
        "settings": {
            "staticLights": false,
            "leftHanded": false,
            "playerHeight": 1.504594087600708,
            "disableSFX": false,
            "reduceDebris": false,
            "noTextsAndHuds": false,
            "advancedHud": true
        },
        "gameStats": {
            "badCutsCount": 0,
            "cutScoreWithoutMultiplier": 0,
            "goodCutsCount": 0,
            "handDistanceTravelled": 0,
            "missedCutsCount": 0,
            "timePlayed": 0.53125,
            "totalScore": 0
        }
    },
    {
        "timestamp": 1572407252,
        "computerName": "budid",
        "isFail": false,
        "isQuit": false,
        "player": "DRACO",
        "song": "Warriors",
        "difficulty": "Expert",
        "score": 558824,
        "fullCombo": false,
        "modifiers": {
            "energyType": 0,
            "noFail": false,
            "instaFail": false,
            "failOnSaberClash": false,
            "enabledObstacleType": 0,
            "fastNotes": false,
            "strictAngles": false,
            "disappearingArrows": false,
            "ghostNotes": false,
            "noBombs": false,
            "songSpeed": 0
        },
        "settings": {
            "staticLights": false,
            "leftHanded": false,
            "playerHeight": 1.504594087600708,
            "disableSFX": false,
            "reduceDebris": false,
            "noTextsAndHuds": false,
            "advancedHud": true
        },
        "gameStats": {
            "badCutsCount": 9,
            "cutScoreWithoutMultiplier": 75276,
            "goodCutsCount": 738,
            "handDistanceTravelled": 914,
            "missedCutsCount": 10,
            "timePlayed": 165.953125,
            "totalScore": 558824
        }
    },
    {
        "timestamp": 1572407078,
        "computerName": "budid",
        "isFail": false,
        "isQuit": false,
        "player": "DRACO",
        "song": "Thunder",
        "difficulty": "Expert",
        "score": 504295,
        "fullCombo": false,
        "modifiers": {
            "energyType": 0,
            "noFail": false,
            "instaFail": false,
            "failOnSaberClash": false,
            "enabledObstacleType": 0,
            "fastNotes": false,
            "strictAngles": false,
            "disappearingArrows": false,
            "ghostNotes": false,
            "noBombs": false,
            "songSpeed": 0
        },
        "settings": {
            "staticLights": false,
            "leftHanded": false,
            "playerHeight": 1.504594087600708,
            "disableSFX": false,
            "reduceDebris": false,
            "noTextsAndHuds": false,
            "advancedHud": true
        },
        "gameStats": {
            "badCutsCount": 7,
            "cutScoreWithoutMultiplier": 66456,
            "goodCutsCount": 639,
            "handDistanceTravelled": 870,
            "missedCutsCount": 5,
            "timePlayed": 177.359375,
            "totalScore": 504295
        }
    },
    {
        "timestamp": 1572406888,
        "computerName": "budid",
        "isFail": false,
        "isQuit": false,
        "player": "DRACO",
        "song": "Believer",
        "difficulty": "Expert",
        "score": 582543,
        "fullCombo": false,
        "modifiers": {
            "energyType": 0,
            "noFail": false,
            "instaFail": false,
            "failOnSaberClash": false,
            "enabledObstacleType": 0,
            "fastNotes": false,
            "strictAngles": false,
            "disappearingArrows": false,
            "ghostNotes": false,
            "noBombs": false,
            "songSpeed": 0
        },
        "settings": {
            "staticLights": false,
            "leftHanded": false,
            "playerHeight": 1.504594087600708,
            "disableSFX": false,
            "reduceDebris": false,
            "noTextsAndHuds": false,
            "advancedHud": true
        },
        "gameStats": {
            "badCutsCount": 14,
            "cutScoreWithoutMultiplier": 81060,
            "goodCutsCount": 772,
            "handDistanceTravelled": 1126,
            "missedCutsCount": 9,
            "timePlayed": 201.890625,
            "totalScore": 582543
        }
    },
    {
        "timestamp": 1572406666,
        "computerName": "budid",
        "isFail": false,
        "isQuit": false,
        "player": "DRACO",
        "song": "custom_level_A6A8F5C9146321B609645EEFB109197E301BFE71",
        "difficulty": "Expert",
        "score": 554688,
        "fullCombo": false,
        "modifiers": {
            "energyType": 0,
            "noFail": false,
            "instaFail": false,
            "failOnSaberClash": false,
            "enabledObstacleType": 0,
            "fastNotes": false,
            "strictAngles": false,
            "disappearingArrows": false,
            "ghostNotes": false,
            "noBombs": false,
            "songSpeed": 0
        },
        "settings": {
            "staticLights": false,
            "leftHanded": false,
            "playerHeight": 1.504594087600708,
            "disableSFX": false,
            "reduceDebris": false,
            "noTextsAndHuds": false,
            "advancedHud": true
        },
        "gameStats": {
            "badCutsCount": 12,
            "cutScoreWithoutMultiplier": 77175,
            "goodCutsCount": 735,
            "handDistanceTravelled": 1055,
            "missedCutsCount": 14,
            "timePlayed": 193.6875,
            "totalScore": 554688
        }
    },
    {
        "timestamp": 1572406445,
        "computerName": "budid",
        "isFail": false,
        "isQuit": false,
        "player": "DRACO",
        "song": "Victorious",
        "difficulty": "Expert",
        "score": 535778,
        "fullCombo": false,
        "modifiers": {
            "energyType": 0,
            "noFail": false,
            "instaFail": false,
            "failOnSaberClash": false,
            "enabledObstacleType": 0,
            "fastNotes": false,
            "strictAngles": false,
            "disappearingArrows": false,
            "ghostNotes": false,
            "noBombs": false,
            "songSpeed": 0
        },
        "settings": {
            "staticLights": false,
            "leftHanded": false,
            "playerHeight": 1.504594087600708,
            "disableSFX": false,
            "reduceDebris": false,
            "noTextsAndHuds": false,
            "advancedHud": true
        },
        "gameStats": {
            "badCutsCount": 4,
            "cutScoreWithoutMultiplier": 70245,
            "goodCutsCount": 669,
            "handDistanceTravelled": 927,
            "missedCutsCount": 1,
            "timePlayed": 175.984375,
            "totalScore": 535778
        }
    },
    {
        "timestamp": 1572406261,
        "computerName": "budid",
        "isFail": false,
        "isQuit": false,
        "player": "DRACO",
        "song": "Victorious",
        "difficulty": "Expert",
        "score": 514507,
        "fullCombo": false,
        "modifiers": {
            "energyType": 0,
            "noFail": false,
            "instaFail": false,
            "failOnSaberClash": false,
            "enabledObstacleType": 0,
            "fastNotes": false,
            "strictAngles": false,
            "disappearingArrows": false,
            "ghostNotes": false,
            "noBombs": false,
            "songSpeed": 0
        },
        "settings": {
            "staticLights": false,
            "leftHanded": false,
            "playerHeight": 1.504594087600708,
            "disableSFX": false,
            "reduceDebris": false,
            "noTextsAndHuds": false,
            "advancedHud": true
        },
        "gameStats": {
            "badCutsCount": 13,
            "cutScoreWithoutMultiplier": 69642,
            "goodCutsCount": 657,
            "handDistanceTravelled": 951,
            "missedCutsCount": 4,
            "timePlayed": 176.0,
            "totalScore": 514507
        }
    },
    {
        "timestamp": 1572406065,
        "song": "#unknown",
        "isFail": false,
        "isQuit": true,
        "computerName": "budid",
        "player": "UNKNOWN",
        "score": 0,
        "modifiers": {
            "energyType": 0,
            "noFail": false,
            "instaFail": false,
            "failOnSaberClash": false,
            "enabledObstacleType": 0,
            "fastNotes": false,
            "strictAngles": false,
            "disappearingArrows": false,
            "ghostNotes": false,
            "noBombs": false,
            "songSpeed": 0
        },
        "settings": {
            "staticLights": false,
            "leftHanded": false,
            "playerHeight": 1.504594087600708,
            "disableSFX": false,
            "reduceDebris": false,
            "noTextsAndHuds": false,
            "advancedHud": true
        },
        "gameStats": {
            "badCutsCount": 2,
            "cutScoreWithoutMultiplier": 654,
            "goodCutsCount": 6,
            "handDistanceTravelled": 24,
            "missedCutsCount": 0,
            "timePlayed": 6.03125,
            "totalScore": 0
        }
    }
]